ucord/__init__.py
ucord/buttonstyle.py
ucord/client.py
ucord/component.py
ucord/embed.py
ucord/guild.py
ucord/interaction.py
ucord/presence.py
ucord/status.py
ucord/user.py
ucord-0.0.3.dist-info/LICENSE
ucord-0.0.3.dist-info/METADATA
ucord-0.0.3.dist-info/WHEEL
ucord-0.0.3.dist-info/top_level.txt
ucord-0.0.3.dist-info/RECORD
