Metadata-Version: 2.1
Name: ucord
Version: 0.0.3
Summary: Minimal Discord bot library for Python
Author-email: Jeff53978 <snikkerzakelijk@gmail.com>
Project-URL: Homepage, https://github.com/Pepper-Diffusion/ucord
Project-URL: Bug Tracker, https://github.com/Pepper-Diffusion/ucord/issues
Classifier: Programming Language :: Python :: 3
Classifier: License :: OSI Approved :: GNU General Public License v3 or later (GPLv3+)
Classifier: Operating System :: OS Independent
Requires-Python: >=3.7
License-File: LICENSE
Requires-Dist: requests
Requires-Dist: websocket-client
